smart_file_organizer/__init__.py
smart_file_organizer/main.py
smart_file_organizer/utils.py
smart_file_organizer_tool-0.1.0.dist-info/licenses/LICENSE
smart_file_organizer_tool-0.1.0.dist-info/METADATA
smart_file_organizer_tool-0.1.0.dist-info/WHEEL
smart_file_organizer_tool-0.1.0.dist-info/entry_points.txt
smart_file_organizer_tool-0.1.0.dist-info/top_level.txt
smart_file_organizer_tool-0.1.0.dist-info/RECORD
