Metadata-Version: 2.4
Name: smart-file-organizer-tool
Version: 0.1.0
Summary: 智能文件整理工具，自动分类下载文件
Home-page: https://github.com/yourusername/smart-file-organizer
Author: 你的名字
Author-email: Your Name <your.email@example.com>
Maintainer-email: Your Name <your.email@example.com>
License: MIT
Project-URL: Homepage, https://github.com/yourusername/smart-file-organizer
Project-URL: Repository, https://github.com/yourusername/smart-file-organizer
Project-URL: Issues, https://github.com/yourusername/smart-file-organizer/issues
Project-URL: Documentation, https://github.com/yourusername/smart-file-organizer#readme
Keywords: file,organizer,automation,macos
Classifier: Programming Language :: Python :: 3.10
Classifier: License :: OSI Approved :: MIT License
Classifier: Operating System :: MacOS
Classifier: Development Status :: 3 - Alpha
Requires-Python: >=3.10
License-File: LICENSE
Requires-Dist: pyyaml>=6.0
Requires-Dist: watchdog>=2.1
Dynamic: author
Dynamic: home-page
Dynamic: license-file
Dynamic: requires-python
